setup.py
distributions/Binomialdistribution.py
distributions/Gaussiandistribution.py
distributions/Generaldistribution.py
distributions/__init__.py
jstnsl_distributions.egg-info/PKG-INFO
jstnsl_distributions.egg-info/SOURCES.txt
jstnsl_distributions.egg-info/dependency_links.txt
jstnsl_distributions.egg-info/not-zip-safe
jstnsl_distributions.egg-info/top_level.txt